grablib/__init__.py
grablib/main.py
tests/__init__.py
tests/test_main.py
redeye_grablib-0.0.2.dist-info/LICENSE.md
redeye_grablib-0.0.2.dist-info/METADATA
redeye_grablib-0.0.2.dist-info/WHEEL
redeye_grablib-0.0.2.dist-info/top_level.txt
redeye_grablib-0.0.2.dist-info/RECORD
