Metadata-Version: 2.1
Name: redeye-grablib
Version: 0.0.2
Summary: A library for retrieving files from HTTP servers.
Home-page: https://github.com/RedEyeApp/grablib
Author: CMSteffen
Author-email: cmsteffen@haxys.net
License: UNKNOWN
Platform: UNKNOWN
Classifier: Programming Language :: Python :: 3
Classifier: License :: CC0 1.0 Universal (CC0 1.0) Public Domain Dedication
Classifier: Operating System :: OS Independent
Requires-Python: >=3.8
Requires-Dist: requests
